{
  "text1" : "Nếu bạn mất hơn 5 năm học TIẾNG ANH",
  "text2" : "Do bạn dùng SỨC NGƯỜI để đi mà không có CÔNG CỤ TỐT hỗ trợ",
  "text3" : "Su Speak",
  "text4" : "VỀ ĐÍCH LÀ ĐƯƠNG NHIÊN. CÂU HỎI LÀ:  BẠN MẤT BAO NHIÊU THỜI GIAN",
  "text5" : "CÔNG CỤ LÀM THAY ĐỔI VẬN TỐC - RÚT NGẮN THỜI GIAN",
  "text6" : "@SuSpeak Copyright 2024",
  "text7" : "Một mã xác thực đã gửi đến email của bạn, hãy nhập vào bên dưới",
  "text8" : "Email verification code",
  "text9" : "Enter email code",
  "text10" : "Sign Up",
  "text11" : "Login",
  "text12" : "Hãy nhập email, phone để chúng tôi gửi mã xác thực cho bạn",
  "text13" : "Enter A Email",
  "text14" : "Enter Number Phone",
  "text15" : "Nhập Password mới để đổi mật khẩu",
  "text16" : "Nhập Password mới",
  "text17" : "Change Password",
  "text18" : "Enter Email and Phone",
  "text19" : "Lặp lại Password",
  "text20" : "MÀU BLUE (nếu bạn nghe dưới 50 lần) - MÀU RED (nhỏ 100 lần) - MÀU YELLOW (lớn 100 lần) - MÀU GREEN (lớn 1000 lần)",
  "text21" : "Su Speak DỊCH TỪ VỰNG từ SÁCH EBOOK VÀ YOUTUBE - LÀM ƠN NHỚ RĂNG: LUÔN CÓ VIDEO GỐC YOUTUBE ĐỂ BẠN XEM VÀ NGHE NGƯỜI ANH NÓI GIỌNG THẬT ĐỂ ĐỐI CHIẾU",
  "primary_palette": "Yellow",
  "text22" : "Chọn file nói ở đây"
}
